Sequential Circuit HDL/5 bit down counter synchronous design methodology/subOne.v
// 2003009

module subOne(
  input wire [4:0] i,
  output wire [4:0] o
);
  assign o = i - 1;
endmodule

Sequential Circuit HDL/5 bit down counter synchronous design methodology/dff.v
// 2003009

module dff(
  input wire clk, set, en,
  input wire [4:0] i,
  output wire [4:0] o
);
  reg [4:0] o_reg;
  wire [4:0] o_next;
  always @(posedge clk, posedge set)
  begin
    if (set)
      o_reg <= 5'b1111;
    else if (en)
      o_reg <= o_next;
  end
  assign o_next = i;
  assign o = o_reg;

endmodule

Sequential Circuit HDL/5 bit down counter synchronous design methodology/_5bitDownMeth.v
// 2003009

module _5bitDownMeth(
  input wire clk, set, en, 
  output wire [4:0] o
);
  wire [4:0] i_temp, o_temp;

  dff uut_dff(
    .clk(clk), .set(set), .en(en),
    .i(i_temp),
    .o(o_temp)
  );
  subOne uut_subOne(
    .i(o_temp),
    .o(i_temp)
  );
  assign o = o_temp;

endmodule

Sequential Circuit HDL/5 bit down counter synchronous design methodology/_5bitDownMeth_tb.v
// 2003009

`timescale 1ns/1ps
module _5bitDownMeth_tb;
reg clk, set, en;
wire [4:0] o;

_5bitDownMeth uut(
  .clk(clk), .set(set), .en(en),
  .o(o)
);

always begin
  clk = ~clk;
  #5;
end

  initial begin
    $dumpfile("_5bitDownMeth_tb.vcd");
    $dumpvars(0, _5bitDownMeth_tb);

    clk <= 0;
    set <= 1;
    en <= 0;
    #10;

    en <= 1;
    set <= 0;
    #150;
    $finish;
  end

  initial begin
    $monitor($time, " clk=%b, set=%b, en=%b, o=%b", clk, set, en, o);
  end

endmodule

Sequential Circuit HDL/5 bit down counter synchronous design methodology/_5bitDownMeth_tb.vcd
$date
	Sat Jun 01 12:35:26 2024
$end
$version
	Icarus Verilog
$end
$timescale
	1ps
$end
$scope module _5bitDownMeth_tb $end
$var wire 5 ! o [4:0] $end
$var reg 1 " clk $end
$var reg 1 # en $end
$var reg 1 $ set $end
$scope module uut $end
$var wire 1 " clk $end
$var wire 1 # en $end
$var wire 5 % o [4:0] $end
$var wire 1 $ set $end
$var wire 5 & o_temp [4:0] $end
$var wire 5 ' i_temp [4:0] $end
$scope module uut_dff $end
$var wire 1 " clk $end
$var wire 1 # en $end
$var wire 5 ( o_next [4:0] $end
$var wire 1 $ set $end
$var wire 5 ) o [4:0] $end
$var wire 5 * i [4:0] $end
$var reg 5 + o_reg [4:0] $end
$upscope $end
$scope module uut_subOne $end
$var wire 5 , i [4:0] $end
$var wire 5 - o [4:0] $end
$upscope $end
$upscope $end
$upscope $end
$enddefinitions $end
$comment Show the parameter values. $end
$dumpall
$end
#0
$dumpvars
b1110 -
b1111 ,
b1111 +
b1110 *
b1111 )
b1110 (
b1110 '
b1111 &
b1111 %
1$
0#
0"
b1111 !
$end
#5000
1"
#10000
0$
1#
0"
#15000
b1101 (
b1101 '
b1101 *
b1101 -
b1110 !
b1110 %
b1110 &
b1110 )
b1110 +
b1110 ,
1"
#20000
0"
#25000
b1100 (
b1100 '
b1100 *
b1100 -
b1101 !
b1101 %
b1101 &
b1101 )
b1101 +
b1101 ,
1"
#30000
0"
#35000
b1011 (
b1011 '
b1011 *
b1011 -
b1100 !
b1100 %
b1100 &
b1100 )
b1100 +
b1100 ,
1"
#40000
0"
#45000
b1010 (
b1010 '
b1010 *
b1010 -
b1011 !
b1011 %
b1011 &
b1011 )
b1011 +
b1011 ,
1"
#50000
0"
#55000
b1001 (
b1001 '
b1001 *
b1001 -
b1010 !
b1010 %
b1010 &
b1010 )
b1010 +
b1010 ,
1"
#60000
0"
#65000
b1000 (
b1000 '
b1000 *
b1000 -
b1001 !
b1001 %
b1001 &
b1001 )
b1001 +
b1001 ,
1"
#70000
0"
#75000
b111 (
b111 '
b111 *
b111 -
b1000 !
b1000 %
b1000 &
b1000 )
b1000 +
b1000 ,
1"
#80000
0"
#85000
b110 (
b110 '
b110 *
b110 -
b111 !
b111 %
b111 &
b111 )
b111 +
b111 ,
1"
#90000
0"
#95000
b101 (
b101 '
b101 *
b101 -
b110 !
b110 %
b110 &
b110 )
b110 +
b110 ,
1"
#100000
0"
#105000
b100 (
b100 '
b100 *
b100 -
b101 !
b101 %
b101 &
b101 )
b101 +
b101 ,
1"
#110000
0"
#115000
b11 (
b11 '
b11 *
b11 -
b100 !
b100 %
b100 &
b100 )
b100 +
b100 ,
1"
#120000
0"
#125000
b10 (
b10 '
b10 *
b10 -
b11 !
b11 %
b11 &
b11 )
b11 +
b11 ,
1"
#130000
0"
#135000
b1 (
b1 '
b1 *
b1 -
b10 !
b10 %
b10 &
b10 )
b10 +
b10 ,
1"
#140000
0"
#145000
b0 (
b0 '
b0 *
b0 -
b1 !
b1 %
b1 &
b1 )
b1 +
b1 ,
1"
#150000
0"
#155000
b11111 (
b11111 '
b11111 *
b11111 -
b0 !
b0 %
b0 &
b0 )
b0 +
b0 ,
1"
