Combinational Circuit HDL/BooleanEQ/BEQ.v
module BEQ
(
    input A, B, C, D,
    output Z
);

wire p, q;
and(p, A, C);
and(q, B, D);
or(Z, p, q);

endmodule

Combinational Circuit HDL/BooleanEQ/BEQ_tb.v
`timescale 1ns/1ps

module BEQ_tb;

reg A;
reg B;
reg C;
reg D;
wire Z;

BEQ uut
(
    .A(A),
    .B(B),
    .C(C),
    .D(D),
    .Z(Z)
);

    initial begin
        $dumpfile("BEQ_tb.vcd");
        $dumpvars(0, BEQ_tb);
        A = 0;
        B = 0;
        C = 0;
        D = 0;
        #20 A = 0; C = 0; B = 0; D = 1;
        #20 A = 0; C = 0; B = 1; D = 0;
        #20 A = 0; C = 0; B = 1; D = 1; 
        #20 A = 0; C = 1; B = 0; D = 0;
        #20 A = 0; C = 1; B = 0; D = 1;
        #20 A = 0; C = 1; B = 1; D = 0;
        #20 A = 0; C = 1; B = 1; D = 1;
        #20 A = 1; C = 0; B = 0; D = 0;
        #20 A = 1; C = 0; B = 0; D = 1;
        #20 A = 1; C = 0; B = 1; D = 0;
        #20 A = 1; C = 0; B = 1; D = 1;
        #20 A = 1; C = 1; B = 0; D = 0; 
        #20 A = 1; C = 1; B = 0; D = 1;
        #20 A = 1; C = 1; B = 1; D = 0;
        #20 A = 1; C = 1; B = 1; D = 1;
        #20 $finish;
    end

    initial begin
        $monitor("A=%b, C=%b, B=%b, D=%b, Z=%b", A, C, B, D, Z);
    end
endmodule

Combinational Circuit HDL/BooleanEQ/BEQ_tb.vcd
$date
	Thu May 16 13:41:03 2024
$end
$version
	Icarus Verilog
$end
$timescale
	1ps
$end
$scope module BEQ_tb $end
$var wire 1 ! Z $end
$var reg 1 " A $end
$var reg 1 # B $end
$var reg 1 $ C $end
$var reg 1 % D $end
$scope module uut $end
$var wire 1 " A $end
$var wire 1 # B $end
$var wire 1 $ C $end
$var wire 1 % D $end
$var wire 1 ! Z $end
$var wire 1 & p $end
$var wire 1 ' q $end
$upscope $end
$upscope $end
$enddefinitions $end
$comment Show the parameter values. $end
$dumpall
$end
#0
$dumpvars
0'
0&
0%
0$
0#
0"
0!
$end
#20000
1%
#40000
0%
1#
#60000
1!
1'
1%
#80000
0!
0'
0%
0#
1$
#100000
1%
#120000
0%
1#
#140000
1!
1'
1%
#160000
0!
0'
0%
0#
0$
1"
#180000
1%
#200000
0%
1#
#220000
1!
1'
1%
#240000
0'
1&
0%
0#
1$
#260000
1%
#280000
0%
1#
#300000
1'
1%
