Sequential Circuit HDL/7 bit reg Sync Enable/_7bitSync.v
// 7 bit Register with synchronous enable input
module _7bitSync(
  input wire clk, rst, en,
  input wire [6:0] d,
  output reg [6:0] q
);
  always @(posedge clk, posedge rst)
    begin
      if (rst)
        q <= 7'b0000_000;
      else if (en)
        q <= d;
    end

endmodule

Sequential Circuit HDL/7 bit reg Sync Enable/_7bitSync_tb.v
`timescale 1ns/1ps

module _7bitSync_tb;
reg clk, rst, en;
reg [6:0] d;
wire [6:0] q;

_7bitSync uut(
  .clk(clk), .rst(rst), .en(en),
  .d(d),
  .q(q)
);

  always #5 clk = ~clk;

  initial begin
    $dumpfile("7bitSync_tb.vcd");
    $dumpvars(0, _7bitSync_tb);

    clk <= 0;
    rst <= 1;
    en <= 0;
    d <= 7'b0000_000;

    #10 rst <= 0; en <= 1;
    #10 d <= 7'b0000_001;
    #10 d <= 7'b0000_010;
    #10 d <= 7'b0000_011;
    #10 d <= 7'b0000_100;
    #10 d <= 7'b0000_101;
    #10 d <= 7'b0000_110;
    #10 d <= 7'b0000_111;
    #10 d <= 7'b0001_000;
    #10;
    $finish;
  end

  initial begin
    $monitor("clk=%b rst=%b en=%b d=%b q=%b", clk, rst, en, d, q);
  end

endmodule

Sequential Circuit HDL/7 bit reg Sync Enable/7bitSync_tb.vcd
$date
	Sat Jun 01 09:28:14 2024
$end
$version
	Icarus Verilog
$end
$timescale
	1ps
$end
$scope module _7bitSync_tb $end
$var wire 7 ! q [6:0] $end
$var reg 1 " clk $end
$var reg 7 # d [6:0] $end
$var reg 1 $ en $end
$var reg 1 % rst $end
$scope module uut $end
$var wire 1 " clk $end
$var wire 7 & d [6:0] $end
$var wire 1 $ en $end
$var wire 1 % rst $end
$var reg 7 ' q [6:0] $end
$upscope $end
$upscope $end
$enddefinitions $end
$comment Show the parameter values. $end
$dumpall
$end
#0
$dumpvars
b0 '
b0 &
1%
0$
b0 #
0"
b0 !
$end
#5000
1"
#10000
1$
0%
0"
#15000
1"
#20000
b1 #
b1 &
0"
#25000
b1 !
b1 '
1"
#30000
b10 #
b10 &
0"
#35000
b10 !
b10 '
1"
#40000
b11 #
b11 &
0"
#45000
b11 !
b11 '
1"
#50000
b100 #
b100 &
0"
#55000
b100 !
b100 '
1"
#60000
b101 #
b101 &
0"
#65000
b101 !
b101 '
1"
#70000
b110 #
b110 &
0"
#75000
b110 !
b110 '
1"
#80000
b111 #
b111 &
0"
#85000
b111 !
b111 '
1"
#90000
b1000 #
b1000 &
0"
#95000
b1000 !
b1000 '
1"
