Combinational Circuit HDL/3 to 8 Decoder/dec.v
module dec 
(
    input x,y,z,
    output [7:0] D
);

assign D[0] = ~x & ~y & ~z;
assign D[1] = ~x & ~y & z;
assign D[2] = ~x & y & ~z;
assign D[3] = ~x & y & z;
assign D[4] = x & ~y & ~z;
assign D[5] = x & ~y & z;
assign D[6] = x & y & ~z;
assign D[7] = x & y & z;

endmodule

Combinational Circuit HDL/3 to 8 Decoder/dec_tb.v
`timescale 1ns/1ps

module dec_tb;
    reg x,y,z;
    wire [7:0] D;

    dec uut(
        .x(x),
        .y(y),
        .z(z),
        .D(D)
    );

    initial begin
        $dumpfile("dec_tb.vcd");
        $dumpvars(0, dec_tb);
        
        x = 1'b0;
        y = 1'b0;
        z = 1'b0;
        #20;

        x = 1'b0;
        y = 1'b0;
        z = 1'b1;
        #20;

        x = 1'b0;
        y = 1'b1;
        z = 1'b0;
        #20;

        x = 1'b0;
        y = 1'b1;
        z = 1'b1;
        #20;

        x = 1'b1;
        y = 1'b0;
        z = 1'b0;
        #20;

        x = 1'b1;
        y = 1'b0;
        z = 1'b1;
        #20;

        x = 1'b1;
        y = 1'b1;
        z = 1'b0;
        #20;

        x = 1'b1;
        y = 1'b1;
        z = 1'b1;
        #20;
        $finish;
    end

    initial begin
        $monitor("x=%b, y=%b, z=%b, D=%b", x, y, z, D);
    end
endmodule

Combinational Circuit HDL/3 to 8 Decoder/dec_case.v
module dec_case
(
    input [2:0] X,
    output reg [7:0] D
);

always @(*)
    begin
        case(X)
            3'b000: D = 8'b00000001;
            3'b001: D = 8'b00000010;
            3'b010: D = 8'b00000100;
            3'b011: D = 8'b00001000;
            3'b100: D = 8'b00010000;
            3'b101: D = 8'b00100000;
            3'b110: D = 8'b01000000;
            3'b111: D = 8'b10000000;
            default: D = 8'b00000001;
        endcase
    end
endmodule

Combinational Circuit HDL/3 to 8 Decoder/dec_if_tb.v
`timescale 1ns/1ps

module dec_if_tb;
    reg [2:0] X;
    wire [7:0] D;

    dec_case uut(
        .X(X),
        .D(D)
    );

    initial begin
        $dumpfile("dec_if_tb.vcd");
        $dumpvars(0, dec_if_tb);

        X = 3'b000;
        #20;

        X = 3'b001;
        #20;

        X = 3'b010;
        #20;

        X = 3'b011;
        #20;

        X = 3'b100;
        #20;

        X = 3'b101;
        #20;

        X = 3'b110;
        #20;

        X = 3'b111;
        #20;

        $finish;
    end

    initial begin
        $monitor("X=%b, D=%b", X, D);
    end
endmodule

Combinational Circuit HDL/3 to 8 Decoder/dec_if_tb.vcd
$date
	Sat Jun 01 00:53:51 2024
$end
$version
	Icarus Verilog
$end
$timescale
	1ps
$end
$scope module dec_if_tb $end
$var wire 8 ! D [7:0] $end
$var reg 3 " X [2:0] $end
$scope module uut $end
$var wire 3 # X [2:0] $end
$var reg 8 $ D [7:0] $end
$upscope $end
$upscope $end
$scope module dec_tb $end
$var wire 8 % D [7:0] $end
$var reg 1 & x $end
$var reg 1 ' y $end
$var reg 1 ( z $end
$scope module uut $end
$var wire 1 & x $end
$var wire 1 ' y $end
$var wire 1 ( z $end
$var wire 8 ) D [7:0] $end
$upscope $end
$upscope $end
$enddefinitions $end
$comment Show the parameter values. $end
$dumpall
$end
#0
$dumpvars
b1 )
0(
0'
0&
b1 %
b1 $
b0 #
b0 "
b1 !
$end
#20000
b10 %
b10 )
b10 !
b10 $
1(
b1 "
b1 #
#40000
b100 %
b100 )
b100 !
b100 $
0(
1'
b10 "
b10 #
#60000
b1000 %
b1000 )
b1000 !
b1000 $
1(
b11 "
b11 #
#80000
b10000 %
b10000 )
b10000 !
b10000 $
0(
0'
1&
b100 "
b100 #
#100000
b100000 %
b100000 )
b100000 !
b100000 $
1(
b101 "
b101 #
#120000
b1000000 %
b1000000 )
b1000000 !
b1000000 $
0(
1'
b110 "
b110 #
#140000
b10000000 %
b10000000 )
b10000000 !
b10000000 $
1(
b111 "
b111 #
