Combinational Circuit HDL/Combinational Circuit/comb.v
module comb
(
    input D, X, A,
    output L
);

assign L = (~D)&(~X)&A | (~D)&X&A | D&(~X)&(~A) | D&X&(~A) | D&X&A; 

endmodule

Combinational Circuit HDL/Combinational Circuit/comb_tb.v
`timescale 1ns/1ps

module comb_tb;

    reg D, X, A;
    wire L;

    comb uut
    (
        .D(D),
        .X(X),
        .A(A),
        .L(L)
    );
    
    initial begin
        $dumpfile("comb_tb.vcd");
        $dumpvars(0, comb_tb);
        
        D = 0; X = 0; A = 0;
        #10;
        
        D = 0; X = 0; A = 1;
        #10;
        
        D = 0; X = 1; A = 0;
        #10;
        
        D = 0; X = 1; A = 1;
        #10;
        
        D = 1; X = 0; A = 0;
        #10;
        
        D = 1; X = 0; A = 1;    
        #10;
        
        D = 1; X = 1; A = 0;
        #10;
        
        D = 1; X = 1; A = 1;
        #10;
    end
    
    initial begin
        $monitor("D=%b, X=%b, A=%b, L=%b", D, X, A, L);
        
    end
endmodule

Combinational Circuit HDL/Combinational Circuit/comb_tb.vcd
$date
	Thu May 16 15:58:39 2024
$end
$version
	Icarus Verilog
$end
$timescale
	1ps
$end
$scope module comb_tb $end
$var wire 1 ! L $end
$var reg 1 " A $end
$var reg 1 # D $end
$var reg 1 $ X $end
$scope module uut $end
$var wire 1 " A $end
$var wire 1 # D $end
$var wire 1 ! L $end
$var wire 1 $ X $end
$upscope $end
$upscope $end
$enddefinitions $end
$comment Show the parameter values. $end
$dumpall
$end
#0
$dumpvars
0$
0#
0"
0!
$end
#10000
1!
1"
#20000
0!
0"
1$
#30000
1!
1"
#40000
0"
0$
1#
#50000
0!
1"
#60000
1!
0"
1$
#70000
1"
