Combinational Circuit HDL/Encoder Case/enc_case.v
module enc_case
(
    input [3:0] Y,
    output reg [1:0] A
);

always @(*)
    case(Y)
        4'b0001: A = 2'b00;
        4'b0010: A = 2'b01;
        4'b0100: A = 2'b10;
        4'b1000: A = 2'b11;
        default: A = 2'b00;
    endcase
endmodule

Combinational Circuit HDL/Encoder Case/enc_case_tb.v
`timescale 1ns/1ps

module enc_case_tb;
    reg [3:0] Y;
    wire [3:0] A;

    enc_case uut(
        .Y(Y),
        .A(A)
    );

    initial begin
        $dumpfile("enc_case_tb.vcd");
        $dumpvars(0, enc_case_tb);
        
        Y[3] = 0; Y[2] = 0; Y[1] = 0; Y[0] = 0;
        #20;
    
        Y[3] = 0; Y[2] = 0; Y[1] = 0; Y[0] = 1;
        #20;

        Y[3] = 0; Y[2] = 0; Y[1] = 1; Y[0] = 0;
        #20;

        Y[3] = 0; Y[2] = 0; Y[1] = 1; Y[0] = 1;
        #20;

        Y[3] = 0; Y[2] = 1; Y[1] = 0; Y[0] = 0;
        #20;

        Y[3] = 0; Y[2] = 1; Y[1] = 0; Y[0] = 1;
        #20;

        Y[3] = 0; Y[2] = 1; Y[1] = 1; Y[0] = 0;
        #20;

        Y[3] = 0; Y[2] = 1; Y[1] = 1; Y[0] = 1;
        #20;

        Y[3] = 1; Y[2] = 0; Y[1] = 0; Y[0] = 0;
        #20;

        Y[3] = 1; Y[2] = 0; Y[1] = 0; Y[0] = 1;
        #20;

        Y[3] = 1; Y[2] = 0; Y[1] = 1; Y[0] = 0;
        #20;

        Y[3] = 1; Y[2] = 0; Y[1] = 1; Y[0] = 1;
        #20;

        Y[3] = 1; Y[2] = 1; Y[1] = 0; Y[0] = 0;
        #20;

        Y[3] = 1; Y[2] = 1; Y[1] = 0; Y[0] = 1; 
        #20;

        Y[3] = 1; Y[2] = 1; Y[1] = 1; Y[0] = 0;
        #20;

        Y[3] = 1; Y[2] = 1; Y[1] = 1; Y[0] = 1;
        #20;

        $finish;
    end

    initial begin
        $monitor("Y = %b, A = %b", Y, A);
    end

endmodule

Combinational Circuit HDL/Encoder Case/enc_case_tb.vcd
$date
	Fri May 31 23:05:26 2024
$end
$version
	Icarus Verilog
$end
$timescale
	1ps
$end
$scope module enc_case_tb $end
$var wire 4 ! A [3:0] $end
$var reg 4 " Y [3:0] $end
$scope module uut $end
$var wire 4 # Y [3:0] $end
$var reg 2 $ A [1:0] $end
$upscope $end
$upscope $end
$enddefinitions $end
$comment Show the parameter values. $end
$dumpall
$end
#0
$dumpvars
b0 $
b0 #
b0 "
b0 !
$end
#20000
b1 "
b1 #
#40000
b1 !
b1 $
b10 "
b10 #
#60000
b0 !
b0 $
b11 "
b11 #
#80000
b10 !
b10 $
b100 "
b100 #
#100000
b0 !
b0 $
b101 "
b101 #
#120000
b110 "
b110 #
#140000
b111 "
b111 #
#160000
b11 !
b11 $
b1000 "
b1000 #
#180000
b0 !
b0 $
b1001 "
b1001 #
#200000
b1010 "
b1010 #
#220000
b1011 "
b1011 #
#240000
b1100 "
b1100 #
#260000
b1101 "
b1101 #
#280000
b1110 "
b1110 #
#300000
b1111 "
b1111 #
