Combinational Circuit HDL/Priority Encoder/pri_enc.v
module pri_enc
(
    input [3:0] Y,
    output [1:0] A
);

assign A[1] = (~Y[3] & Y[2]) | (Y[3]);
assign A[0] =(~Y[3] & ~Y[2] & Y[1]) | (Y[3]);
endmodule

Combinational Circuit HDL/Priority Encoder/pri_enc_tb.v
`timescale 1ns/1ps

module pri_enc_tb;
    reg [3:0] Y;
    wire [1:0] A;

    pri_enc uut(
        .Y(Y),
        .A(A)
    );

    initial begin
        $dumpfile("pri_enc_tb.vcd");
        $dumpvars(0, pri_enc_tb);

        Y = 4'b0000;
        #10;
        Y = 4'b0001;
        #10;
        Y = 4'b0010;
        #10;
        Y = 4'b0011;
        #10;
        Y = 4'b0100;
        #10;
        Y = 4'b0101;
        #10;
        Y = 4'b0110;
        #10;
        Y = 4'b0111;
        #10;
        Y = 4'b1000;
        #10;
        Y = 4'b1001;
        #10;
        Y = 4'b1010;
        #10;
        Y = 4'b1011;
        #10;
        Y = 4'b1100;
        #10;
        Y = 4'b1101;
        #10;
        Y = 4'b1110;
        #10;
        Y = 4'b1111;
        #10;
        $finish;
    end

    initial begin
        $monitor("Y=%b, A=%b", Y, A);
    end
endmodule

Combinational Circuit HDL/Priority Encoder/pri_enc_tb.vcd
$date
	Sat Jun 01 00:01:54 2024
$end
$version
	Icarus Verilog
$end
$timescale
	1ps
$end
$scope module pri_enc_tb $end
$var wire 2 ! A [1:0] $end
$var reg 4 " Y [3:0] $end
$scope module uut $end
$var wire 4 # Y [3:0] $end
$var wire 2 $ A [1:0] $end
$upscope $end
$upscope $end
$enddefinitions $end
$comment Show the parameter values. $end
$dumpall
$end
#0
$dumpvars
b0 $
b0 #
b0 "
b0 !
$end
#10000
b1 "
b1 #
#20000
b1 !
b1 $
b10 "
b10 #
#30000
b11 "
b11 #
#40000
b10 !
b10 $
b100 "
b100 #
#50000
b101 "
b101 #
#60000
b110 "
b110 #
#70000
b111 "
b111 #
#80000
b11 !
b11 $
b1000 "
b1000 #
#90000
b1001 "
b1001 #
#100000
b1010 "
b1010 #
#110000
b1011 "
b1011 #
#120000
b1100 "
b1100 #
#130000
b1101 "
b1101 #
#140000
b1110 "
b1110 #
#150000
b1111 "
b1111 #
