Sequential Circuit HDL/16 bit register/_16bit.v
module _16bit(
  input wire clk, rst,
  input wire [15:0] i,
  output reg [15:0] o
);
  always @(posedge clk or posedge rst) begin
    if (rst)
      o <= 16'b0000_0000_0000_0000;
    else
      o <= i;
  end

endmodule

Sequential Circuit HDL/16 bit register/_16bit_tb.v
`timescale 1ns / 1ps

module _16bit_tb;
  reg clk, rst;
  reg [15:0] i;
  wire [15:0] o;

  _16bit uut (
    .clk(clk),
    .rst(rst),
    .i(i),
    .o(o)
  );

  always begin
    clk = ~clk;
    #5;
  end

  initial begin
    $dumpfile("16bit_tb.vcd");
    $dumpvars(0, _16bit_tb);

    clk <= 0;
    rst <= 1;
    i <= 16'b0000_0000_0000_0000;
    #10 rst <= 0;
    #10 i <= 16'b0000_0000_0000_0001;
    #10 i <= 16'b0000_0000_0000_0010;
    #10 i <= 16'b0000_0000_0000_0100;
    #10 $finish;
  end

  initial begin
    $monitor("clk=%b, rst=%b, i=%16b, o=%16b", clk, rst, i, o);
  end

endmodule

Sequential Circuit HDL/16 bit register/16bit_tb.vcd
$date
	Sat Jun 01 09:22:14 2024
$end
$version
	Icarus Verilog
$end
$timescale
	1ps
$end
$scope module _16bit_tb $end
$var wire 16 ! o [15:0] $end
$var reg 1 " clk $end
$var reg 16 # i [15:0] $end
$var reg 1 $ rst $end
$scope module uut $end
$var wire 1 " clk $end
$var wire 16 % i [15:0] $end
$var wire 1 $ rst $end
$var reg 16 & o [15:0] $end
$upscope $end
$upscope $end
$enddefinitions $end
$comment Show the parameter values. $end
$dumpall
$end
#0
$dumpvars
b0 &
b0 %
1$
b0 #
0"
b0 !
$end
#5000
1"
#10000
0$
0"
#15000
1"
#20000
b1 #
b1 %
0"
#25000
b1 !
b1 &
1"
#30000
b10 #
b10 %
0"
#35000
b10 !
b10 &
1"
#40000
b100 #
b100 %
0"
#45000
b100 !
b100 &
1"
